pytest_copie/__init__.py
pytest_copie/plugin.py
pytest_copie/py.typed
pytest_copie-0.3.1.dist-info/METADATA
pytest_copie-0.3.1.dist-info/WHEEL
pytest_copie-0.3.1.dist-info/entry_points.txt
pytest_copie-0.3.1.dist-info/licenses/AUTHORS.rst
pytest_copie-0.3.1.dist-info/licenses/LICENSE
pytest_copie-0.3.1.dist-info/RECORD
