Metadata-Version: 2.4
Name: pytest-copie
Version: 0.3.1
Summary: The pytest plugin for your copier templates 📒
Project-URL: Homepage, https://github.com/12rambau/pytest-copie
Author-email: Pierrick Rambaud <pierrick.rambaud49@gmail.com>
License: MIT
License-File: AUTHORS.rst
License-File: LICENSE
Keywords: Python,copier,pytest,pytest-plugin
Classifier: Development Status :: 3 - Alpha
Classifier: Intended Audience :: Developers
Classifier: License :: OSI Approved :: MIT License
Classifier: Programming Language :: Python :: 3.9
Classifier: Programming Language :: Python :: 3.10
Classifier: Programming Language :: Python :: 3.11
Classifier: Programming Language :: Python :: 3.12
Requires-Python: >=3.9
Requires-Dist: copier
Requires-Dist: deprecated>=1.2.14
Requires-Dist: plumbum
Requires-Dist: pytest
Provides-Extra: doc
Requires-Dist: sphinx-autoapi; extra == 'doc'
Requires-Dist: sphinx-copybutton; extra == 'doc'
Requires-Dist: sphinx-immaterial; extra == 'doc'
Requires-Dist: sphinx>=6.2.1; extra == 'doc'
Requires-Dist: sphinxemoji; extra == 'doc'
Provides-Extra: test
Requires-Dist: pytest; extra == 'test'
Requires-Dist: pytest-cov; extra == 'test'
Requires-Dist: pytest-deadfixtures; extra == 'test'
